zxcvbn/main.py
zxcvbn/__init__.py
zxcvbn/matching.py
zxcvbn/scoring.py
zxcvbn/generated/frequency_lists.json
zxcvbn/generated/adjacency_graphs.json
zxcvbn/scripts/build_keyboard_adjacency_graph.py
zxcvbn/scripts/build_frequency_lists.py
zxcvbn/data/tv_and_movie_freqlist5001-6000.html
zxcvbn/data/tv_and_movie_freqlist6001-7000.html
zxcvbn/data/us_census_2000_female_first.txt
zxcvbn/data/tv_and_movie_freqlist7001-8000.html
zxcvbn/data/tv_and_movie_freqlist16001-18000.html
zxcvbn/data/tv_and_movie_freqlist12001-14000.html
zxcvbn/data/tv_and_movie_freqlist34001-36000.html
zxcvbn/data/tv_and_movie_freqlist9001-10000.html
zxcvbn/data/tv_and_movie_freqlist28001-30000.html
zxcvbn/data/tv_and_movie_freqlist22001-24000.html
zxcvbn/data/us_census_2000_male_first.txt
zxcvbn/data/tv_and_movie_freqlist18001-20000.html
zxcvbn/data/tv_and_movie_freqlist14001-16000.html
zxcvbn/data/common_passwords.txt
zxcvbn/data/tv_and_movie_freqlist2001-3000.html
zxcvbn/data/tv_and_movie_freqlist40001-41284.html
zxcvbn/data/tv_and_movie_freqlist24001-26000.html
zxcvbn/data/README
zxcvbn/data/tv_and_movie_freqlist3001-4000.html
zxcvbn/data/tv_and_movie_freqlist1-1000.html
zxcvbn/data/us_census_2000_surnames.txt
zxcvbn/data/tv_and_movie_freqlist26001-28000.html
zxcvbn/data/tv_and_movie_freqlist32001-34000.html
zxcvbn/data/tv_and_movie_freqlist38001-40000.html
zxcvbn/data/tv_and_movie_freqlist20001-22000.html
zxcvbn/data/tv_and_movie_freqlist36001-38000.html
zxcvbn/data/tv_and_movie_freqlist1001-2000.html
zxcvbn/data/tv_and_movie_freqlist10001-12000.html
zxcvbn/data/tv_and_movie_freqlist8001-9000.html
zxcvbn/data/tv_and_movie_freqlist4001-5000.html
zxcvbn/data/tv_and_movie_freqlist30001-32000.html
zxcvbn_py3-1.1.dist-info/RECORD
zxcvbn_py3-1.1.dist-info/METADATA
zxcvbn_py3-1.1.dist-info/WHEEL
zxcvbn_py3-1.1.dist-info/DESCRIPTION.rst
zxcvbn_py3-1.1.dist-info/metadata.json
zxcvbn_py3-1.1.dist-info/pbr.json
zxcvbn_py3-1.1.dist-info/top_level.txt
