Metadata-Version: 2.0
Name: zxcvbn-py3
Version: 1.1
Summary: Password strength estimator
Home-page: https://github.com/gordon86/python-zxcvbn
Author: Gordon Vu
Author-email: gordon.vu@gmail.com
License: UNKNOWN
Platform: any
Classifier: Intended Audience :: Developers
Classifier: Programming Language :: Python :: 2
Classifier: Programming Language :: Python :: 2.6
Classifier: Programming Language :: Python :: 2.7
Classifier: Programming Language :: Python :: 3
Classifier: Programming Language :: Python :: 3.2
Classifier: Programming Language :: Python :: 3.3
Classifier: Programming Language :: Python :: 3.4
